apachelabs/__init__.py
apachelabs/client.py
apachelabs/config.py
apachelabs-2.0.0.dist-info/LICENSE
apachelabs-2.0.0.dist-info/METADATA
apachelabs-2.0.0.dist-info/WHEEL
apachelabs-2.0.0.dist-info/top_level.txt
apachelabs-2.0.0.dist-info/RECORD
