Metadata-Version: 2.1
Name: apachelabs
Version: 2.0.0
Summary: Apache Labs API is a Python package that uses Mistral and Hugging Face to create a simple and unified API system to use all of the Apache Labs models
Home-page: https://github.com/yourusername/apachelabs
Author: Apache Labs
Author-email: your.email@example.com
Classifier: Programming Language :: Python :: 3
Classifier: License :: OSI Approved :: MIT License
Classifier: Operating System :: OS Independent
Requires-Python: >=3.7
License-File: LICENSE
Requires-Dist: mistralai
